Metadata-Version: 1.1
Name: NoelNLP
Version: 0.0.2
Summary: Swahili Stop-words and Stemmer
Home-page: UNKNOWN
Author: Noel Moses Mwadende
Author-email: mosesnoel02@gmail.com
License: MIT
Keywords: Swahili Stop-words,NLTK,NLP
Platform: UNKNOWN
Classifier: Development Status :: 3 - Alpha
Classifier: Intended Audience :: Developers
Classifier: License :: OSI Approved :: MIT License
Classifier: Programming Language :: Python :: 3
